archiverr_client-1.0.2.data/scripts/archiverr
src/Config.py
src/Utilities.py
src/__init__.py
src/__main__.py
src/client.py
src/constants.py
src/config/__init__.py
archiverr_client-1.0.2.dist-info/METADATA
archiverr_client-1.0.2.dist-info/WHEEL
archiverr_client-1.0.2.dist-info/top_level.txt
archiverr_client-1.0.2.dist-info/RECORD
